[
  {
    "name": "age on Earth",
    "test_code": "verify do\n  labeled \"age on Earth\" do\n    expected = Some 31.69)\n    actual = age \"Earth\" 1000000000\n    label \"expected\" expected\n    label \"actual\" actual\n    ensure (actual +- expected)"
  },
  {
    "name": "age on Mercury",
    "test_code": "verify do\n  labeled \"age on Mercury\" do\n    expected = Some 280.88)\n    actual = age \"Mercury\" 2134835688\n    label \"expected\" expected\n    label \"actual\" actual\n    ensure (actual +- expected)"
  },
  {
    "name": "age on Venus",
    "test_code": "verify do\n  labeled \"age on Venus\" do\n    expected = Some 9.78)\n    actual = age \"Venus\" 189839836\n    label \"expected\" expected\n    label \"actual\" actual\n    ensure (actual +- expected)"
  },
  {
    "name": "age on Mars",
    "test_code": "verify do\n  labeled \"age on Mars\" do\n    expected = Some 35.88)\n    actual = age \"Mars\" 2129871239\n    label \"expected\" expected\n    label \"actual\" actual\n    ensure (actual +- expected)"
  },
  {
    "name": "age on Jupiter",
    "test_code": "verify do\n  labeled \"age on Jupiter\" do\n    expected = Some 2.41)\n    actual = age \"Jupiter\" 901876382\n    label \"expected\" expected\n    label \"actual\" actual\n    ensure (actual +- expected)"
  },
  {
    "name": "age on Saturn",
    "test_code": "verify do\n  labeled \"age on Saturn\" do\n    expected = Some 2.15)\n    actual = age \"Saturn\" 2000000000\n    label \"expected\" expected\n    label \"actual\" actual\n    ensure (actual +- expected)"
  },
  {
    "name": "age on Uranus",
    "test_code": "verify do\n  labeled \"age on Uranus\" do\n    expected = Some 0.46)\n    actual = age \"Uranus\" 1210123456\n    label \"expected\" expected\n    label \"actual\" actual\n    ensure (actual +- expected)"
  },
  {
    "name": "age on Neptune",
    "test_code": "verify do\n  labeled \"age on Neptune\" do\n    expected = Some 0.35)\n    actual = age \"Neptune\" 1821023456\n    label \"expected\" expected\n    label \"actual\" actual\n    ensure (actual +- expected)"
  },
  {
    "name": "invalid planet causes error",
    "test_code": "verify do\n  labeled \"invalid planet causes error\" do\n    expected = None\n    actual = age \"Sun\" 680804807\n    label \"expected\" expected\n    label \"actual\" actual\n    ensure (actual +- expected)"
  }
]
